README.rst
setup.py
bin/__init__.py
bin/dsms_report.py
dsms_cmd/__init__.py
dsms_cmd/dsms_cmd.py
dsms_cmd/templates/standard.j2
dsms_report_cli.egg-info/PKG-INFO
dsms_report_cli.egg-info/SOURCES.txt
dsms_report_cli.egg-info/dependency_links.txt
dsms_report_cli.egg-info/entry_points.txt
dsms_report_cli.egg-info/pbr.json
dsms_report_cli.egg-info/requires.txt
dsms_report_cli.egg-info/top_level.txt